fdfdpy
