Metadata-Version: 2.1
Name: fdfdpy
Version: 0.1.2
Summary: Electromagnetic Finite Difference Frequency Domain Solver
Home-page: https://github.com/fancompute/fdfdpy
Author: Tyler Hughes, Momchil Minkov, Ian Williamson
Author-email: tylerwhughes91@gmail.com
License: UNKNOWN
Platform: UNKNOWN
Classifier: Programming Language :: Python :: 3
Classifier: License :: OSI Approved :: MIT License
Classifier: Operating System :: OS Independent
